async_magic/.__init__.py.swp
async_magic/.__init__.py.un~
async_magic/__init__.py
async_magic-0.0.1.dist-info/WHEEL
async_magic-0.0.1.dist-info/METADATA
async_magic-0.0.1.dist-info/RECORD
