Metadata-Version: 1.2
Name: async_magic
Version: 0.0.1
Summary: Define an async_magic for IPython that fake the async keyword at top level
Home-page: https://github.com/Carreau/async_magic
License: UNKNOWN
Author: Matthias Bussonnier
Author-email: bussonniermatthias@gmail.com
Requires-Python: >=3.5
Classifier: License :: OSI Approved :: MIT License
